{
  "session_dir": "logs\\live\\sessions\\20260417T213810.304834Z_stage1_harvest",
  "session_name": "stage1_harvest",
  "pid": 14376,
  "started_at": "2026-04-17T21:38:10.304834+00:00",
  "ended_at": null,
  "do_submit": true,
  "target_ticks": null,
  "target_hours": 8.0,
  "cycles_total": 303,
  "unique_turns": 275,
  "duplicate_turns": 28,
  "idle_cycles": 5,
  "fallback_count": 0,
  "submit_attempts": 274,
  "submit_successes": 274,
  "submit_failures": 0,
  "error_events": 0,
  "rate_limit_events": 0,
  "network_events": 0,
  "timeout_events": 0,
  "transport_events": 0,
  "action_breakdown": {
    "hold": 5,
    "command": 298
  },
  "submit_skip_reasons": {
    "idle_arena": 5,
    "duplicate_turn_guard": 24
  },
  "error_codes": {
    "0": 274
  },
  "avg_next_turn_in": 0.9615,
  "avg_latency_ms": 267.36,
  "max_plantation_count": 1,
  "max_isolated_count": 0,
  "max_critical_bridge_count": 0,
  "max_construction_count": 1,
  "low_confidence_turns": 273,
  "last_turn": 308,
  "last_timestamp": "2026-04-17T21:43:08.883769+00:00",
  "last_main_position": [
    243,
    49
  ],
  "last_main_hp": 40,
  "last_main_ttf": 6,
  "_sum_next_turn_in": 291.32300000000004,
  "_sum_latency_ms": 81009.0
}